{
  "title": "Saturday night 24 June 2023 on ABC TV",
  "url": "https://www.abc.net.au/rage/playlist/saturday-night-24-june-2023-on-abc-tv/102517934",
  "special": "Pale Waves guest program rage",
  "timeslot": "night",
  "date": "2023-06-24",
  "tracks": [
    {
      "artist": "PALE WAVES",
      "song": "Eighteen",
      "label": "Sony",
      "timeslot": "23:30:00"
    },
    {
      "artist": "THE VERVE",
      "song": "Bittersweet Symphony",
      "label": "Virgin",
      "timeslot": "23:30:00"
    },
    {
      "artist": "DAVID BOWIE",
      "song": "Life On Mars?",
      "label": "Independent",
      "timeslot": "23:30:00"
    },
    {
      "artist": "THE CURE",
      "song": "Friday I'm In Love",
      "label": "Warner",
      "timeslot": "23:30:00"
    },
    {
      "artist": "GARBAGE",
      "song": "I Think I'm Paranoid",
      "label": "Mushroom",
      "timeslot": "23:30:00"
    },
    {
      "artist": "HOLE",
      "song": "Celebrity Skin",
      "label": "Universal (MCA)",
      "timeslot": "23:30:00"
    },
    {
      "artist": "OASIS",
      "song": "Supersonic",
      "label": "Sony",
      "timeslot": "00:00:00"
    },
    {
      "artist": "SINEAD O'CONNOR",
      "song": "Nothing Compares 2 U",
      "label": "EMI",
      "timeslot": "00:00:00"
    },
    {
      "artist": "ARCADE FIRE",
      "song": "The Suburbs",
      "label": "Spunk/EMI",
      "timeslot": "00:00:00"
    },
    {
      "artist": "PULP",
      "song": "Common People",
      "label": "Mercury",
      "timeslot": "00:00:00"
    },
    {
      "artist": "THE BLUE NILE",
      "song": "The Downtown Lights",
      "label": "LINN",
      "timeslot": "00:00:00"
    },
    {
      "artist": "COLDPLAY",
      "song": "Yellow",
      "label": "EMI",
      "timeslot": "00:00:00"
    },
    {
      "artist": "ARCTIC MONKEYS",
      "song": "R U Mine",
      "label": "EMI",
      "timeslot": "00:30:00"
    },
    {
      "artist": "ARCTIC MONKEYS",
      "song": "Fluorescent Adolescent",
      "label": "Virgin",
      "timeslot": "00:30:00"
    },
    {
      "artist": "TRAVIS",
      "song": "Why Does It Always Rain On Me?",
      "label": "Sony",
      "timeslot": "00:30:00"
    },
    {
      "artist": "THE CRANBERRIES",
      "song": "Linger",
      "label": "Independent",
      "timeslot": "00:30:00"
    },
    {
      "artist": "TENACIOUS D",
      "song": "Tribute",
      "label": "Sony",
      "timeslot": "00:30:00"
    },
    {
      "artist": "PAPA ROACH",
      "song": "Last Resort",
      "label": "Universal",
      "timeslot": "00:30:00"
    },
    {
      "artist": "EVANESCENCE",
      "song": "Bring Me To Life",
      "label": "Sony",
      "timeslot": "00:30:00"
    },
    {
      "artist": "DEFTONES",
      "song": "Be Quiet And Drive",
      "label": "Warner",
      "timeslot": "01:00:00"
    },
    {
      "artist": "AVRIL LAVIGNE",
      "song": "Sk8er Boi",
      "label": "BMG",
      "timeslot": "01:00:00"
    },
    {
      "artist": "AVRIL LAVIGNE",
      "song": "Complicated",
      "label": "BMG",
      "timeslot": "01:00:00"
    },
    {
      "artist": "ALANIS MORISSETTE",
      "song": "Ironic",
      "label": "Warner",
      "timeslot": "01:00:00"
    },
    {
      "artist": "JAMIROQUAI",
      "song": "Virtual Insanity",
      "label": "Sony",
      "timeslot": "01:00:00"
    },
    {
      "artist": "EMINEM",
      "song": "The Real Slim Shady",
      "label": "Universal",
      "timeslot": "01:00:00"
    },
    {
      "artist": "KENDRICK LAMAR",
      "song": "Humble",
      "label": "Universal",
      "timeslot": "01:00:00"
    },
    {
      "artist": "TRAVIS SCOTT ft. DRAKE",
      "song": "Sicko Mode",
      "label": "Good Music",
      "timeslot": "01:00:00"
    },
    {
      "artist": "BILLIE EILISH",
      "song": "Happier Than Ever",
      "label": "Darkroom/Interscope Records",
      "timeslot": "01:30:00"
    },
    {
      "artist": "SILK SONIC (BRUNO MARS, ANDERSON .PAAK)",
      "song": "Leave The Door Open",
      "label": "Atlantic",
      "timeslot": "01:30:00"
    },
    {
      "artist": "BRITNEY SPEARS",
      "song": "Toxic",
      "label": "BMG",
      "timeslot": "01:30:00"
    },
    {
      "artist": "ERIC PRYDZ",
      "song": "Call On Me",
      "label": "MOS/EMI",
      "timeslot": "01:30:00"
    },
    {
      "artist": "DAFT PUNK",
      "song": "Around The World",
      "label": "Virgin",
      "timeslot": "01:30:00"
    },
    {
      "artist": "DRAKE",
      "song": "Hotline Bling",
      "label": "Universal",
      "timeslot": "01:30:00"
    },
    {
      "artist": "CALVIN HARRIS and DUA LIPA",
      "song": "One Kiss",
      "label": "Sony",
      "timeslot": "01:30:00"
    },
    {
      "artist": "REBECCA BLACK",
      "song": "Friday",
      "label": "Independent",
      "timeslot": "02:00:00"
    },
    {
      "artist": "LADY GAGA",
      "song": "Judas",
      "label": "Universal",
      "timeslot": "02:00:00"
    },
    {
      "artist": "MILEY CYRUS",
      "song": "Flowers",
      "label": "Columbia",
      "timeslot": "02:00:00"
    },
    {
      "artist": "SHANIA TWAIN",
      "song": "Man! I Feel Like A Woman!",
      "label": "Mercury",
      "timeslot": "02:00:00"
    },
    {
      "artist": "TAYLOR SWIFT",
      "song": "You Belong With Me",
      "label": "Universal",
      "timeslot": "02:00:00"
    },
    {
      "artist": "THE 1975",
      "song": "Sex",
      "label": "Sony",
      "timeslot": "02:00:00"
    },
    {
      "artist": "BUSTED",
      "song": "What I Go To School For",
      "label": "Universal",
      "timeslot": "02:00:00"
    },
    {
      "artist": "PARAMORE",
      "song": "That's What You Get",
      "label": "Warner",
      "timeslot": "02:30:00"
    },
    {
      "artist": "PARAMORE",
      "song": "The Only Exception",
      "label": "Warner",
      "timeslot": "02:30:00"
    },
    {
      "artist": "PALE WAVES",
      "song": "Television Romance",
      "label": "Dirty Hit",
      "timeslot": "02:30:00"
    },
    {
      "artist": "PALE WAVES",
      "song": "Lies",
      "label": "Dirty Hit",
      "timeslot": "02:30:00"
    },
    {
      "artist": "PALE WAVES",
      "song": "Unwanted",
      "label": "Dirty Hit",
      "timeslot": "02:30:00"
    },
    {
      "artist": "PALE WAVES",
      "song": "Clean",
      "label": "Dirty Hit",
      "timeslot": "02:30:00"
    },
    {
      "artist": "PALE WAVES",
      "song": "Jealousy",
      "label": "Dirty Hit",
      "timeslot": "02:30:00"
    },
    {
      "artist": "PALE WAVES",
      "song": "Reasons To Live",
      "label": "Dirty Hit",
      "timeslot": "02:30:00"
    },
    {
      "artist": "PALE WAVES",
      "song": "Fall To Pieces",
      "label": "Dirty Hit",
      "timeslot": "02:30:00"
    },
    {
      "artist": "PALE WAVES",
      "song": "Easy",
      "label": "Dirty Hit",
      "timeslot": "03:00:00"
    },
    {
      "artist": "PALE WAVES",
      "song": "She's My Religion",
      "label": "Dirty Hit",
      "timeslot": "03:00:00"
    },
    {
      "artist": "PALE WAVES",
      "song": "Change",
      "label": "Dirty Hit",
      "timeslot": "03:00:00"
    },
    {
      "artist": "PALE WAVES",
      "song": "One More Time",
      "label": "Dirty Hit",
      "timeslot": "03:00:00"
    },
    {
      "artist": "PALE WAVES",
      "song": "Noises",
      "label": "Dirty Hit",
      "timeslot": "03:00:00"
    },
    {
      "artist": "PALE WAVES",
      "song": "Kiss",
      "label": "Sony",
      "timeslot": "03:00:00"
    },
    {
      "artist": "OASIS",
      "song": "Wonderwall",
      "label": "Sony",
      "timeslot": "03:00:00"
    },
    {
      "artist": "OASIS",
      "song": "Champagne Supernova",
      "label": "SBME",
      "timeslot": "03:00:00"
    },
    {
      "artist": "OASIS",
      "song": "Morning Glory",
      "label": "Sony",
      "timeslot": "03:30:00"
    },
    {
      "artist": "STONE ROSES",
      "song": "Fools Gold",
      "label": "Universal (MCA)",
      "timeslot": "03:30:00"
    },
    {
      "artist": "STONE ROSES",
      "song": "She Bangs The Drums",
      "label": "Universal (MCA)",
      "timeslot": "03:30:00"
    },
    {
      "artist": "STONE ROSES",
      "song": "I Wanna Be Adored",
      "label": "BMG",
      "timeslot": "03:30:00"
    },
    {
      "artist": "JOY DIVISION - LIVE",
      "song": "She's Lost Control",
      "label": "Festival",
      "timeslot": "03:30:00"
    },
    {
      "artist": "JOY DIVISION",
      "song": "Love Will Tear Us Apart",
      "label": "Festival",
      "timeslot": "03:30:00"
    },
    {
      "artist": "JOY DIVISION - LIVE",
      "song": "Transmission",
      "label": "Fest/Mush",
      "timeslot": "03:30:00"
    },
    {
      "artist": "HAPPY MONDAYS",
      "song": "Step On",
      "label": "Festival",
      "timeslot": "04:00:00"
    },
    {
      "artist": "HAPPY MONDAYS",
      "song": "Lazyitis",
      "label": "Festival",
      "timeslot": "04:00:00"
    },
    {
      "artist": "HAPPY MONDAYS",
      "song": "Wrote For Luck",
      "label": "Festival",
      "timeslot": "04:00:00"
    },
    {
      "artist": "NEW ORDER",
      "song": "Blue Monday",
      "label": "Factory",
      "timeslot": "04:00:00"
    },
    {
      "artist": "NEW ORDER",
      "song": "Crystal",
      "label": "Warner",
      "timeslot": "04:00:00"
    },
    {
      "artist": "NEW ORDER",
      "song": "Confusion",
      "label": "Festival",
      "timeslot": "04:00:00"
    },
    {
      "artist": "THE CHEMICAL BROTHERS",
      "song": "Hey Boy, Hey Girl",
      "label": "Virgin",
      "timeslot": "04:00:00"
    },
    {
      "artist": "THE CHEMICAL BROTHERS",
      "song": "Star Guitar",
      "label": "Virgin",
      "timeslot": "04:00:00"
    },
    {
      "artist": "THE FALL",
      "song": "Why Are People Grudgeful",
      "label": "Fest/Mush",
      "timeslot": "04:30:00"
    },
    {
      "artist": "THE BUZZCOCKS",
      "song": "Ever Fallen In Love",
      "label": "BMG",
      "timeslot": "04:30:00"
    },
    {
      "artist": "LAMB",
      "song": "Gorecki",
      "label": "Mercury",
      "timeslot": "04:30:00"
    },
    {
      "artist": "THE VERVE",
      "song": "The Drugs Don't Work",
      "label": "Virgin",
      "timeslot": "04:30:00"
    },
    {
      "artist": "THE SMITHS",
      "song": "This Charming Man",
      "label": "Festival",
      "timeslot": "04:30:00"
    },
    {
      "artist": "THE CHARLATANS",
      "song": "One To Another",
      "label": "Universal (MCA)",
      "timeslot": "04:30:00"
    },
    {
      "artist": "808 STATE",
      "song": "Pacific State",
      "label": "WEA",
      "timeslot": "04:30:00"
    },
    {
      "artist": "MANTRA OF THE COSMOS",
      "song": "Gorilla Guerilla",
      "label": "BMG",
      "timeslot": "05:00:00"
    },
    {
      "artist": "JUWAN",
      "song": "Mr. If I Don't Got It (I'll Get It)",
      "label": "Forever Ever",
      "timeslot": "05:00:00"
    },
    {
      "artist": "PINCH POINTS",
      "song": "Woomera",
      "label": "Roolette Records",
      "timeslot": "05:00:00"
    },
    {
      "artist": "TOVE LO",
      "song": "i like U",
      "label": "Pretty Swede Records",
      "timeslot": "05:00:00"
    },
    {
      "artist": "TIA GOSTELOW",
      "song": "Early Twenties",
      "label": "Lovely Records",
      "timeslot": "05:00:00"
    },
    {
      "artist": "SLOWDIVE",
      "song": "Kisses",
      "label": "Dead Oceans",
      "timeslot": "05:00:00"
    },
    {
      "artist": "KING GIZZARD and THE LIZARD WIZARD",
      "song": "Dragon",
      "label": "KGLW",
      "timeslot": "05:00:00"
    },
    {
      "artist": "BATTLESNAKE",
      "song": "Nazarenne Extreme (censored version)",
      "label": "Independent",
      "timeslot": "05:00:00"
    },
    {
      "artist": "ANGIE MCMAHON",
      "song": "Saturn Returning",
      "label": "Independent",
      "timeslot": "05:30:00"
    },
    {
      "artist": "THE TESKEY BROTHERS",
      "song": "Remember The Time",
      "label": "Ivy League",
      "timeslot": "05:30:00"
    },
    {
      "artist": "BLACK CAB",
      "song": "Superfans!",
      "label": "Interstate 40 Music",
      "timeslot": "05:30:00"
    },
    {
      "artist": "JACK LADDER",
      "song": "Home Alone",
      "label": "Endless Recordings",
      "timeslot": "05:30:00"
    },
    {
      "artist": "FOO FIGHTERS",
      "song": "The Teacher",
      "label": "Roswell Records",
      "timeslot": "05:30:00"
    },
    {
      "artist": "THE HIVES",
      "song": "Countdown To Shutdown",
      "label": "FUGA Music",
      "timeslot": "05:30:00"
    },
    {
      "artist": "TA-KU ft. OMAR, DAISY WORLD and ROMDERFUL",
      "song": "Smile",
      "label": "Future Classic",
      "timeslot": "06:00:00"
    },
    {
      "artist": "DAFT PUNK ft. JULIAN CASABLANCAS and THE VOIDZ",
      "song": "Infinity Repeating (2013 Demo)",
      "label": "Columbia",
      "timeslot": "06:00:00"
    },
    {
      "artist": "LASTLINGS",
      "song": "Gravity",
      "label": "Liberation",
      "timeslot": "06:00:00"
    },
    {
      "artist": "CLEA",
      "song": "Bad Behaviour",
      "label": "Dew Process",
      "timeslot": "06:00:00"
    },
    {
      "artist": "THE RIONS",
      "song": "Minivan",
      "label": "Independent",
      "timeslot": "06:00:00"
    },
    {
      "artist": "AMAARAE",
      "song": "Wasted Eyes",
      "label": "Interscope Records",
      "timeslot": "06:00:00"
    },
    {
      "artist": "LIME CORDIALE",
      "song": "Imposter Syndrome",
      "label": "Chugg",
      "timeslot": "06:00:00"
    },
    {
      "artist": "BABE RAINBOW",
      "song": "Sunshine",
      "label": "Eureka Music",
      "timeslot": "06:00:00"
    },
    {
      "artist": "EASY BROWNS",
      "song": "Frog Bit",
      "label": "Critter Records",
      "timeslot": "06:30:00"
    },
    {
      "artist": "AWA MBAYE",
      "song": "Black Girl Magic",
      "label": "Independent",
      "timeslot": "06:30:00"
    },
    {
      "artist": "KATY STEELE",
      "song": "Big Star",
      "label": "Independent",
      "timeslot": "06:30:00"
    },
    {
      "artist": "CAITLIN and THE PONYBOYS",
      "song": "Even Cowgirls Cry",
      "label": "Independent",
      "timeslot": "06:30:00"
    },
    {
      "artist": "PJ HARVEY",
      "song": "I Inside The Old I Dying",
      "label": "Liberator",
      "timeslot": "06:30:00"
    },
    {
      "artist": "VALLIS ALPS",
      "song": "You and I",
      "label": "Independent",
      "timeslot": "06:30:00"
    },
    {
      "artist": "MIDDLE KIDS",
      "song": "Bootleg Firecracker",
      "label": "EMI",
      "timeslot": "06:30:00"
    }
  ]
}