{
  "title": "Friday night 1 March 2024 on ABC TV",
  "special": "New Music Show",
  "timeslot": "night",
  "date": "2024-03-01",
  "url": "https://www.abc.net.au/rage/playlist/friday-night-1-march-2024-on-abc-tv/103535264",
  "tracks": [
    {
      "artist": "THATBOYKWAME",
      "song": "Anecdote",
      "label": "Independent",
      "timeslot": "01:30:00"
    },
    {
      "artist": "ST. VINCENT",
      "song": "Broken Man",
      "label": "Virgin",
      "timeslot": "01:30:00"
    },
    {
      "artist": "WEEKND, THE, MADONNA, PLAYBOI CARTI",
      "song": "Popular (censored version)",
      "label": "Republic Records",
      "timeslot": "01:30:00"
    },
    {
      "artist": "MISSY HIGGINS",
      "song": "You Should Run",
      "label": "Eleven: A Music Company",
      "timeslot": "01:30:00"
    },
    {
      "artist": "BAT FOR LASHES",
      "song": "The Dream Of Delphi",
      "label": "Mercury KX",
      "timeslot": "02:00:00"
    },
    {
      "artist": "ALFIE TEMPLEMAN",
      "song": "Eyes Wide Shut",
      "label": "Chess Club",
      "timeslot": "02:00:00"
    },
    {
      "artist": "MAYA HAWKE",
      "song": "Missing Out",
      "label": "Mom and Pop",
      "timeslot": "02:00:00"
    },
    {
      "artist": "BEANS",
      "song": "Dreaming Daisy",
      "label": "Fuzz Club Records",
      "timeslot": "02:00:00"
    },
    {
      "artist": "KINGS OF LEON",
      "song": "Mustang",
      "label": "Capitol",
      "timeslot": "02:00:00"
    },
    {
      "artist": "MAGNETS",
      "song": "Speak",
      "label": "Independent",
      "timeslot": "02:00:00"
    },
    {
      "artist": "TELENOVA",
      "song": "Teardrop",
      "label": "EMI",
      "timeslot": "02:00:00"
    },
    {
      "artist": "DECLAN MCKENNA",
      "song": "Mulholland's Dinner and Wine",
      "label": "Sony",
      "timeslot": "02:00:00"
    },
    {
      "artist": "DRAKE ft. SEXYY RED and SZA",
      "song": "Rich Baby Daddy",
      "label": "OVO",
      "timeslot": "02:00:00"
    },
    {
      "artist": "WEEKND, THE, MADONNA, PLAYBOI CARTI",
      "song": "Popular",
      "label": "Republic Records",
      "timeslot": "02:30:00"
    },
    {
      "artist": "CENTRAL CEE",
      "song": "I Will",
      "label": "Columbia",
      "timeslot": "02:30:00"
    },
    {
      "artist": "FRED AGAIN... and LIL YACHTY and OVERMONO",
      "song": "Stayinit",
      "label": "Warner",
      "timeslot": "02:30:00"
    },
    {
      "artist": "TIERRA WHACK",
      "song": "27 Club",
      "label": "Interscope Records",
      "timeslot": "02:30:00"
    },
    {
      "artist": "JOE GODDARD",
      "song": "New World (Flow)",
      "label": "Domino",
      "timeslot": "02:30:00"
    },
    {
      "artist": "DRUNK MUMS",
      "song": "New Australia",
      "label": "Independent",
      "timeslot": "02:30:00"
    },
    {
      "artist": "MONEY BOYS",
      "song": "New Skin / New Century",
      "label": "Independent",
      "timeslot": "02:30:00"
    },
    {
      "artist": "ELSY WAMEYO",
      "song": "Sinner",
      "label": "Insanity Records",
      "timeslot": "02:30:00"
    },
    {
      "artist": "JAGUAR JONZE",
      "song": "Victim Impact Statement",
      "label": "Nettwerk Records",
      "timeslot": "03:00:00"
    },
    {
      "artist": "1999 WRITE THE FUTURE ft. EYEDRESS",
      "song": "rUN tHE FaDE",
      "label": "88Rising",
      "timeslot": "03:00:00"
    },
    {
      "artist": "THE MYSTERINES",
      "song": "Stray",
      "label": "Fiction / Virgin",
      "timeslot": "03:00:00"
    },
    {
      "artist": "NICK WARD",
      "song": "Gimme",
      "label": "EMI",
      "timeslot": "03:00:00"
    },
    {
      "artist": "RUI GABRIEL",
      "song": "Target",
      "label": "Carpark",
      "timeslot": "03:00:00"
    },
    {
      "artist": "ROYEL OTIS",
      "song": "Foam",
      "label": "Ourness",
      "timeslot": "03:30:00"
    },
    {
      "artist": "UNKNOWN T ft. LOYLE CARNER",
      "song": "Hocus Pocus",
      "label": "Universal",
      "timeslot": "03:30:00"
    },
    {
      "artist": "KUCKA ft. FLUME",
      "song": "One More Night",
      "label": "Soothsayer",
      "timeslot": "03:30:00"
    },
    {
      "artist": "DENT MAY ft. JORDANA",
      "song": "Coasting On Fumes",
      "label": "Carpark",
      "timeslot": "03:30:00"
    },
    {
      "artist": "LAST DINOSAURS",
      "song": "Keys To Your Civic",
      "label": "Nettwerk Records",
      "timeslot": "03:30:00"
    },
    {
      "artist": "DAPHNIE and RUNWAY MORNINGS",
      "song": "Chasing Shadows",
      "label": "Independent",
      "timeslot": "03:30:00"
    },
    {
      "artist": "DIZZEE RASCAL",
      "song": "Switch And Explode",
      "label": "Big Dirtee Records",
      "timeslot": "03:30:00"
    },
    {
      "artist": "LIL YACHTY",
      "song": "Something Ether",
      "label": "Quality Control",
      "timeslot": "03:30:00"
    },
    {
      "artist": "CALVIN HARRIS ft. RAG'N'BONE MAN",
      "song": "Lovers In A Past Life",
      "label": "Sony",
      "timeslot": "03:30:00"
    },
    {
      "artist": "BETWEEN YOU and ME",
      "song": "In The Middle",
      "label": "BYAM Records",
      "timeslot": "03:30:00"
    },
    {
      "artist": "GIRL AND GIRL",
      "song": "Hello",
      "label": "Sub Pop / Virgin",
      "timeslot": "04:00:00"
    },
    {
      "artist": "PSYCHEDELIC PORN CRUMPETS",
      "song": "Pillhouse (Papa Moonshine)",
      "label": "What Reality? Records",
      "timeslot": "04:00:00"
    },
    {
      "artist": "THE LEMON TWIGS",
      "song": "They Don't Know How To Fall In Place",
      "label": "Captured Tracks",
      "timeslot": "04:00:00"
    },
    {
      "artist": "EMILY WURRAMARA",
      "song": "Magic Woman Dancing",
      "label": "ABC Music",
      "timeslot": "04:00:00"
    },
    {
      "artist": "MAGGIE ROGERS",
      "song": "Don't Forget Me",
      "label": "Capitol",
      "timeslot": "04:00:00"
    },
    {
      "artist": "MGMT ft. CHRISTINE and THE QUEENS",
      "song": "Dancing In Babylon",
      "label": "Mom and Pop",
      "timeslot": "04:00:00"
    },
    {
      "artist": "JUSTICE",
      "song": "Generator",
      "label": "Ed Banger / Because",
      "timeslot": "04:00:00"
    },
    {
      "artist": "MOUNT KIMBIE",
      "song": "Fishbrain",
      "label": "Warp",
      "timeslot": "04:30:00"
    },
    {
      "artist": "MELANIE MARTINEZ",
      "song": "Faerie Soiree",
      "label": "Atlantic",
      "timeslot": "04:30:00"
    },
    {
      "artist": "TONES AND I",
      "song": "Dreaming",
      "label": "Bad Batch Records",
      "timeslot": "04:30:00"
    },
    {
      "artist": "THE VOVOS",
      "song": "Pink Milk",
      "label": "Blossom Rot Records",
      "timeslot": "04:30:00"
    },
    {
      "artist": "HIGHSCHOOL",
      "song": "Doesn't Matter",
      "label": "PIAS",
      "timeslot": "04:30:00"
    },
    {
      "artist": "JET CITY SPORTS CLUB",
      "song": "Sunny Morning",
      "label": "Independent",
      "timeslot": "04:30:00"
    },
    {
      "artist": "SAYA GRAY",
      "song": "AA Bouquet For Your 180 Face",
      "label": "Dirty Hit",
      "timeslot": "04:30:00"
    },
    {
      "artist": "IDLES",
      "song": "Grace",
      "label": "Liberator",
      "timeslot": "04:30:00"
    },
    {
      "artist": "DONNY BENET",
      "song": "Forbidden Love",
      "label": "Donnyland Records",
      "timeslot": "05:00:00"
    },
    {
      "artist": "ROYEL OTIS",
      "song": "Foam (clean version)",
      "label": "Ourness",
      "timeslot": "05:00:00"
    },
    {
      "artist": "ALEKSIAH",
      "song": "24",
      "label": "Independent",
      "timeslot": "05:00:00"
    },
    {
      "artist": "KHRUANGBIN",
      "song": "May Ninth",
      "label": "Dead Oceans / Night Time Stories",
      "timeslot": "05:00:00"
    },
    {
      "artist": "MELANIE MARTINEZ",
      "song": "Faerie Soiree (censored version)",
      "label": "Atlantic",
      "timeslot": "05:00:00"
    },
    {
      "artist": "VAMPIRE WEEKEND",
      "song": "Gen-X Cops",
      "label": "Columbia",
      "timeslot": "05:00:00"
    },
    {
      "artist": "BECCA HATCH",
      "song": "Bass Keeps Calling",
      "label": "Forever Ever",
      "timeslot": "05:00:00"
    },
    {
      "artist": "TONES AND I",
      "song": "Dreaming (clean version)",
      "label": "Bad Batch Records",
      "timeslot": "05:30:00"
    },
    {
      "artist": "3% ft. TIA GOSTELOW",
      "song": "Sleezy Steezy Cool",
      "label": "1788 Records",
      "timeslot": "05:30:00"
    },
    {
      "artist": "SHANAE",
      "song": "Outside",
      "label": "Independent",
      "timeslot": "05:30:00"
    },
    {
      "artist": "COSMO'S MIDNIGHT ft. FRANC MOODY",
      "song": "Fantasy",
      "label": "Nite High",
      "timeslot": "05:30:00"
    },
    {
      "artist": "ALLDAY",
      "song": "Access",
      "label": "Dew Process / Island Records",
      "timeslot": "05:30:00"
    },
    {
      "artist": "THE BUOYS",
      "song": "Settle Petal",
      "label": "Arcadia Records",
      "timeslot": "05:30:00"
    },
    {
      "artist": "EMILY WURRAMARA",
      "song": "Magic Woman Dancing",
      "label": "ABC Music",
      "timeslot": "05:30:00"
    },
    {
      "artist": "HOCKEY DAD",
      "song": "Base Camp",
      "label": "Farmer and The Owl / BMG",
      "timeslot": "05:30:00"
    }
  ]
}