{
  "title": "Thursday night 25 December 2025 on ABC Entertains",
  "special": "rage Christmas Special",
  "timeslot": "night",
  "date": "2025-12-25",
  "url": "https://www.abc.net.au/rage/playlist/thursday-night-25-december-2025-on-abc-entertains/106145748",
  "tracks": [
    {
      "artist": "RUN DMC",
      "song": "Christmas In Hollis",
      "label": "Arista",
      "timeslot": "00:00:00"
    },
    {
      "artist": "OUTKAST",
      "song": "Player's Ball",
      "label": "BMG",
      "timeslot": "00:00:00"
    },
    {
      "artist": "SNOOP DOGGY DOGG",
      "song": "Santa Claus Goes Straight To The Ghetto",
      "label": "Interscope Records",
      "timeslot": "00:30:00"
    },
    {
      "artist": "GUCCI MANE",
      "song": "St. Brick Intro",
      "label": "WEA",
      "timeslot": "00:30:00"
    },
    {
      "artist": "GUCCI MANE",
      "song": "Jingle Bales Intro",
      "label": "WEA",
      "timeslot": "00:30:00"
    },
    {
      "artist": "JIM JONES",
      "song": "Bad Santa Intro",
      "label": "Shock",
      "timeslot": "00:30:00"
    },
    {
      "artist": "CHILLINIT",
      "song": "Bad Santa",
      "label": "Virgin",
      "timeslot": "00:30:00"
    },
    {
      "artist": "LIL NAS X",
      "song": "Holiday",
      "label": "Sony",
      "timeslot": "00:30:00"
    },
    {
      "artist": "RUN THE JEWELS",
      "song": "A Christmas Fucking Miracle",
      "label": "Fool's Gold Records",
      "timeslot": "00:30:00"
    },
    {
      "artist": "RUN THE JEWELS",
      "song": "Walking In The Snow",
      "label": "Jewel Runners",
      "timeslot": "00:30:00"
    },
    {
      "artist": "RATKING",
      "song": "Snow Beach",
      "label": "Hot Charity / Remote Control",
      "timeslot": "01:00:00"
    },
    {
      "artist": "NO DOUBT",
      "song": "Oi To The World",
      "label": "Interscope Records",
      "timeslot": "01:00:00"
    },
    {
      "artist": "TLC",
      "song": "Sleigh Ride",
      "label": "La Face Records",
      "timeslot": "01:00:00"
    },
    {
      "artist": "MARIAH CAREY",
      "song": "All I Want For Christmas Is You",
      "label": "Sony",
      "timeslot": "01:00:00"
    },
    {
      "artist": "ARIANA GRANDE",
      "song": "Santa Tell Me",
      "label": "Republic Records",
      "timeslot": "01:00:00"
    }
  ]
}