{
  "title": "Saturday night 1 November 2025 on ABC Entertains",
  "special": "Wu-Tang Clan special",
  "timeslot": "night",
  "date": "2025-11-01",
  "url": "https://www.abc.net.au/rage/playlist/saturday-night-1-november-2025-on-abc-entertains/105959824",
  "tracks": [
    {
      "artist": "THE WU-TANG CLAN",
      "song": "C.R.E.A.M.",
      "label": "BMG",
      "timeslot": "00:00:00"
    },
    {
      "artist": "THE WU-TANG CLAN",
      "song": "Method Man",
      "label": "BMG",
      "timeslot": "00:00:00"
    },
    {
      "artist": "THE WU-TANG CLAN",
      "song": "Wu-Tang Clan Ain't Nuthin'",
      "label": "BMG",
      "timeslot": "00:00:00"
    },
    {
      "artist": "THE WU-TANG CLAN",
      "song": "Da Mystery Of Chessboxin'",
      "label": "BMG",
      "timeslot": "00:00:00"
    },
    {
      "artist": "THE WU-TANG CLAN",
      "song": "Can It All Be So Simple?",
      "label": "BMG",
      "timeslot": "00:00:00"
    },
    {
      "artist": "THE WU-TANG CLAN",
      "song": "Triumph",
      "label": "BMG",
      "timeslot": "00:00:00"
    },
    {
      "artist": "THE WU-TANG CLAN",
      "song": "It's Yourz",
      "label": "BMG",
      "timeslot": "00:30:00"
    },
    {
      "artist": "THE WU-TANG CLAN",
      "song": "Reunited",
      "label": "BMG",
      "timeslot": "00:30:00"
    },
    {
      "artist": "THE WU-TANG CLAN",
      "song": "Gravel Pit",
      "label": "Sony",
      "timeslot": "00:30:00"
    },
    {
      "artist": "THE WU-TANG CLAN",
      "song": "Protect Ya Neck (The Jump Off)",
      "label": "Sony",
      "timeslot": "00:30:00"
    },
    {
      "artist": "THE WU-TANG CLAN",
      "song": "Pinky Ring",
      "label": "Sony",
      "timeslot": "00:30:00"
    },
    {
      "artist": "WU-TANG KILLA BEEZ",
      "song": "Killa Beez",
      "label": "Shock",
      "timeslot": "00:30:00"
    },
    {
      "artist": "TEXAS and WU-TANG CLAN",
      "song": "Hi",
      "label": "BMG",
      "timeslot": "01:00:00"
    }
  ]
}