{
  "title": "Sunday night 8 June 2025 on ABC Entertains",
  "special": "New Music Show",
  "timeslot": "night",
  "date": "2025-06-08",
  "url": "https://www.abc.net.au/rage/playlist/sunday-night-8-june-2025-on-abc-entertains/105386194",
  "tracks": [
    {
      "artist": "LORDE",
      "song": "Man Of The Year",
      "label": "Sweat It Out",
      "timeslot": "23:30:00"
    },
    {
      "artist": "NINAJIRACHI",
      "song": "Fuck My Computer",
      "label": "NLV Records",
      "timeslot": "23:30:00"
    },
    {
      "artist": "DRIFTING CLOUDS",
      "song": "Bawuypawuy",
      "label": "Independent",
      "timeslot": "23:30:00"
    },
    {
      "artist": "DRUGDEALER ft. WEYES BLOOD",
      "song": "Real Thing",
      "label": "Mexican Summer",
      "timeslot": "23:30:00"
    },
    {
      "artist": "THE MOVING STILLS",
      "song": "Can't Be Like This Forever",
      "label": "Independent",
      "timeslot": "23:30:00"
    },
    {
      "artist": "PIG PEN",
      "song": "Rabid Beach",
      "label": "Flatspot Records",
      "timeslot": "23:30:00"
    },
    {
      "artist": "PSYCHEDELIC PORN CRUMPETS",
      "song": "Incubator (V2000)",
      "label": "What Reality? Records",
      "timeslot": "23:30:00"
    },
    {
      "artist": "SELVE",
      "song": "Breaking Into Heaven",
      "label": "Community Music",
      "timeslot": "00:00:00"
    },
    {
      "artist": "KING PRINCESS",
      "song": "RIP KP",
      "label": "Mushroom Music / Section1",
      "timeslot": "00:00:00"
    },
    {
      "artist": "TURNSTILE",
      "song": "Look Out For Me",
      "label": "Roadrunner Records",
      "timeslot": "00:00:00"
    },
    {
      "artist": "SEX MASK",
      "song": "Circe",
      "label": "Independent",
      "timeslot": "00:00:00"
    },
    {
      "artist": "WINSTON SURFSHIRT",
      "song": "One Sugar",
      "label": "Sweat It Out",
      "timeslot": "00:00:00"
    },
    {
      "artist": "YUMI ZOUMA",
      "song": "Blister",
      "label": "Nettwerk Records",
      "timeslot": "00:00:00"
    },
    {
      "artist": "ALEX G",
      "song": "Afterlife",
      "label": "RCA",
      "timeslot": "00:00:00"
    },
    {
      "artist": "MILEY CYRUS",
      "song": "Easy Lover",
      "label": "Columbia",
      "timeslot": "00:00:00"
    },
    {
      "artist": "ZION GARCIA",
      "song": "Sensitive",
      "label": "Independent",
      "timeslot": "00:30:00"
    },
    {
      "artist": "DZ DEATHRAYS",
      "song": "Sideways",
      "label": "Independent",
      "timeslot": "00:30:00"
    }
  ]
}