{
  "title": "Saturday night 1 June 2024 on ABC TV",
  "url": "https://www.abc.net.au/rage/playlist/saturday-night-1-june-2024-on-abc-tv/103921422",
  "special": "Boris guest program rage",
  "timeslot": "night",
  "date": "2024-06-01",
  "tracks": [
    {
      "artist": "BORIS",
      "song": "Pink",
      "label": null,
      "timeslot": "23:30:00"
    },
    {
      "artist": "NICK CAVE",
      "song": "From Her To Eternity (Live in Copenhagen, 2018)",
      "label": "Mute / BMG",
      "timeslot": "23:30:00"
    },
    {
      "artist": "THE BIRTHDAY PARTY - LIVE,",
      "song": "Deep In The Woods",
      "label": "Independent",
      "timeslot": "23:30:00"
    },
    {
      "artist": "THE BIRTHDAY PARTY - LIVE",
      "song": "Release The Bats",
      "label": "Mushroom",
      "timeslot": "23:30:00"
    },
    {
      "artist": "THE BIRTHDAY PARTY - LIVE",
      "song": "Dead Song",
      "label": "Mushroom",
      "timeslot": "00:00:00"
    },
    {
      "artist": "MELVINS",
      "song": "Honey Bucket",
      "label": "Warner",
      "timeslot": "00:00:00"
    },
    {
      "artist": "MELVINS",
      "song": "Hooch",
      "label": "Atlantic",
      "timeslot": "00:00:00"
    },
    {
      "artist": "THE JESUS LIZARD",
      "song": "Gladiator",
      "label": null,
      "timeslot": "00:00:00"
    },
    {
      "artist": "BAD BRAINS",
      "song": "I Against I",
      "label": "Sony",
      "timeslot": "00:00:00"
    },
    {
      "artist": "THE CRAMPS",
      "song": "Bikini Girls With Machine Guns",
      "label": "EMI",
      "timeslot": "00:00:00"
    },
    {
      "artist": "THE SAINTS",
      "song": "(I'm) Stranded",
      "label": "EMI",
      "timeslot": "00:00:00"
    },
    {
      "artist": "RADIO BIRDMAN - LIVE",
      "song": "Search and Destroy",
      "label": "Warner",
      "timeslot": "00:00:00"
    },
    {
      "artist": "CRIME and THE CITY SOLUTION",
      "song": "American Twilight",
      "label": "Independent",
      "timeslot": "00:00:00"
    },
    {
      "artist": "PRIMAL SCREAM",
      "song": "Kowalski",
      "label": "Sony",
      "timeslot": "00:30:00"
    },
    {
      "artist": "BUTTHOLE SURFERS",
      "song": "Pepper",
      "label": "EMI",
      "timeslot": "00:30:00"
    },
    {
      "artist": "JAPAN",
      "song": "Ghosts",
      "label": "CBS",
      "timeslot": "00:30:00"
    },
    {
      "artist": "CAN",
      "song": "Vitamin C",
      "label": "United Artist",
      "timeslot": "00:30:00"
    },
    {
      "artist": "MY BLOODY VALENTINE",
      "song": "Only Shallow",
      "label": "Creation / Shock",
      "timeslot": "00:30:00"
    },
    {
      "artist": "KIYOHARU",
      "song": "Youen (Live)",
      "label": "Fullface Records",
      "timeslot": "00:30:00"
    },
    {
      "artist": "QUEENS OF THE STONE AGE",
      "song": "Go With The Flow",
      "label": "Universal",
      "timeslot": "01:00:00"
    },
    {
      "artist": "JACK WHITE",
      "song": "I'm Shakin'",
      "label": "Sony",
      "timeslot": "01:00:00"
    },
    {
      "artist": "NEIL YOUNG",
      "song": "Dead Man",
      "label": "Warner",
      "timeslot": "01:00:00"
    },
    {
      "artist": "YES",
      "song": "Owner Of A Lonely Heart",
      "label": "Warner",
      "timeslot": "01:00:00"
    },
    {
      "artist": "KIYOHARU",
      "song": "Saint",
      "label": "Fullface Records",
      "timeslot": "01:00:00"
    },
    {
      "artist": "THE CURE",
      "song": "Boys Don't Cry",
      "label": "Warner",
      "timeslot": "01:00:00"
    },
    {
      "artist": "BAUHAUS",
      "song": "She's In Parties",
      "label": "Virgin",
      "timeslot": "01:30:00"
    },
    {
      "artist": "A-HA",
      "song": "Take On Me",
      "label": "Sony",
      "timeslot": "01:30:00"
    },
    {
      "artist": "ULTRAVOX",
      "song": "The Thin Wall",
      "label": "Festival",
      "timeslot": "01:30:00"
    },
    {
      "artist": "ECHO and THE BUNNYMEN",
      "song": "Porcupine",
      "label": "Warner",
      "timeslot": "01:30:00"
    },
    {
      "artist": "SMASHING PUMPKINS",
      "song": "The Everlasting Gaze",
      "label": "Virgin",
      "timeslot": "01:30:00"
    },
    {
      "artist": "THE DAMNED",
      "song": "Smash It Up",
      "label": "Warner",
      "timeslot": "01:30:00"
    },
    {
      "artist": "DAISY CHAINSAW",
      "song": "Love Your Money",
      "label": "Mushroom",
      "timeslot": "01:30:00"
    },
    {
      "artist": "THE CULT",
      "song": "Wild Flower",
      "label": "Virgin",
      "timeslot": "01:30:00"
    },
    {
      "artist": "THE DOORS - LIVE",
      "song": "The End",
      "label": "Warner",
      "timeslot": "02:00:00"
    },
    {
      "artist": "THE DOORS",
      "song": "Light My Fire",
      "label": "Warner",
      "timeslot": "02:00:00"
    },
    {
      "artist": "IGGY and THE STOOGES - LIVE",
      "song": "Loose",
      "label": "Shock",
      "timeslot": "02:00:00"
    },
    {
      "artist": "IGGY and THE STOOGES - LIVE",
      "song": "I Wanna Be Your Dog",
      "label": "Shock",
      "timeslot": "02:00:00"
    },
    {
      "artist": "ZOOT",
      "song": "Turn Your Head (Live on Hitscene, 1970)",
      "label": "ABC",
      "timeslot": "02:30:00"
    },
    {
      "artist": "ZOOT",
      "song": "I'm Only Sleeping (Live on GTK, 1971)",
      "label": "ABC",
      "timeslot": "02:30:00"
    },
    {
      "artist": "ZOOT",
      "song": "Eleanor Rigby",
      "label": "Polydor",
      "timeslot": "02:30:00"
    },
    {
      "artist": "THE HARD-ONS",
      "song": "Crazy Crazy Eyes",
      "label": "Festival",
      "timeslot": "02:30:00"
    },
    {
      "artist": "KYUSS",
      "song": "Green Machine",
      "label": "Warner",
      "timeslot": "02:30:00"
    },
    {
      "artist": "FU MANCHU",
      "song": "Written In Stone",
      "label": "Shock",
      "timeslot": "02:30:00"
    },
    {
      "artist": "BRUJERIA",
      "song": "La Migra",
      "label": "Roadrunner",
      "timeslot": "02:30:00"
    },
    {
      "artist": "AC/DC - LIVE",
      "song": "Touch Too Much",
      "label": "Sony",
      "timeslot": "02:30:00"
    },
    {
      "artist": "BLACK SABBATH",
      "song": "War Pigs (Live, 1970)",
      "label": "WWA",
      "timeslot": "03:00:00"
    },
    {
      "artist": "DEEP PURPLE - LIVE",
      "song": "Mistreated",
      "label": "Polydor",
      "timeslot": "03:00:00"
    },
    {
      "artist": "JUDAS PRIEST",
      "song": "Painkiller",
      "label": "CBS",
      "timeslot": "03:00:00"
    },
    {
      "artist": "SLAYER",
      "song": "Angel Of Death (Live)",
      "label": "Sony",
      "timeslot": "03:00:00"
    },
    {
      "artist": "THIN LIZZY",
      "song": "Whiskey In The Jar",
      "label": "Karussell",
      "timeslot": "03:30:00"
    },
    {
      "artist": "NAILS",
      "song": "I Don't Want To Know You",
      "label": "Nuclear Blast",
      "timeslot": "03:30:00"
    },
    {
      "artist": "BORIS",
      "song": "My Name Is Blank",
      "label": "Relapse",
      "timeslot": "03:30:00"
    },
    {
      "artist": "BORIS",
      "song": "Reincarnation Rose",
      "label": "Fangs Anal Satan",
      "timeslot": "03:30:00"
    },
    {
      "artist": "BORIS",
      "song": "Serial Tear",
      "label": "u-desper Records / Fangs Anal Satan",
      "timeslot": "03:30:00"
    },
    {
      "artist": "BORIS",
      "song": "Statement",
      "label": "Independent",
      "timeslot": "03:30:00"
    },
    {
      "artist": "PALEDUSK ft. VIGORMAN",
      "song": "I'm Ready To Die For My Friends",
      "label": "Greyscale Records",
      "timeslot": "03:30:00"
    },
    {
      "artist": "BABYMETAL",
      "song": "Karate",
      "label": "Sony",
      "timeslot": "04:00:00"
    },
    {
      "artist": "BABYMETAL",
      "song": "Distortion",
      "label": "Cooking Vinyl",
      "timeslot": "04:00:00"
    },
    {
      "artist": "CRYSTAL LAKE",
      "song": "Aeon",
      "label": "Sharptone",
      "timeslot": "04:00:00"
    },
    {
      "artist": "CRYSTAL LAKE",
      "song": "In Forever",
      "label": "Sharptone",
      "timeslot": "04:00:00"
    },
    {
      "artist": "CRYSTAL LAKE",
      "song": "Devilcry",
      "label": "Sharptone",
      "timeslot": "04:00:00"
    },
    {
      "artist": "CRIME and THE CITY SOLUTION",
      "song": "On Every Train",
      "label": "Festival",
      "timeslot": "04:00:00"
    },
    {
      "artist": "CRIME and THE CITY SOLUTION",
      "song": "I Have The Gun",
      "label": "Festival",
      "timeslot": "04:00:00"
    },
    {
      "artist": "THE BIRTHDAY PARTY",
      "song": "Nick The Stripper",
      "label": "Mushroom",
      "timeslot": "04:00:00"
    },
    {
      "artist": "THE BIRTHDAY PARTY - LIVE",
      "song": "Dead Joe",
      "label": "Mushroom",
      "timeslot": "04:30:00"
    },
    {
      "artist": "THE BIRTHDAY PARTY - LIVE",
      "song": "Junkyard - from video 'Pleasure Heads Must Burn'",
      "label": "Festival",
      "timeslot": "04:30:00"
    },
    {
      "artist": "NICK CAVE and KYLIE MINOGUE",
      "song": "Where The Wild Roses Grow",
      "label": "Mushroom",
      "timeslot": "04:30:00"
    },
    {
      "artist": "NICK CAVE and THE BAD SEEDS",
      "song": "The Weeping Song",
      "label": "Mushroom",
      "timeslot": "04:30:00"
    },
    {
      "artist": "NICK CAVE and THE BAD SEEDS",
      "song": "Red Right Hand",
      "label": "Mushroom",
      "timeslot": "04:30:00"
    },
    {
      "artist": "NICK CAVE and THE BAD SEEDS",
      "song": "Dig, Lazarus, Dig!!!",
      "label": "Virgin",
      "timeslot": "04:30:00"
    },
    {
      "artist": "MADONNA",
      "song": "Jump",
      "label": "Warner",
      "timeslot": "05:00:00"
    },
    {
      "artist": "BEASTIE BOYS",
      "song": "Intergalactic",
      "label": "EMI",
      "timeslot": "05:00:00"
    },
    {
      "artist": "OK GO",
      "song": "I Won't Let You Down",
      "label": "BMG",
      "timeslot": "05:00:00"
    },
    {
      "artist": "ELASTICA",
      "song": "Car Song",
      "label": "Universal",
      "timeslot": "05:00:00"
    },
    {
      "artist": "OASIS",
      "song": "Acquiesce",
      "label": "Sony",
      "timeslot": "05:00:00"
    },
    {
      "artist": "INXS",
      "song": "Original Sin",
      "label": "Warner",
      "timeslot": "05:00:00"
    },
    {
      "artist": "THE POLICE",
      "song": "So Lonely",
      "label": "A and M Records",
      "timeslot": "05:00:00"
    },
    {
      "artist": "LAST DINOSAURS",
      "song": "Paranoia Paradise",
      "label": "Los Dinos / Nettwerk",
      "timeslot": "05:00:00"
    },
    {
      "artist": "THE KILLERS",
      "song": "Read My Mind",
      "label": "Universal",
      "timeslot": "05:30:00"
    },
    {
      "artist": "ROSALIA",
      "song": "Tuya",
      "label": "Columbia",
      "timeslot": "05:30:00"
    },
    {
      "artist": "ARLO PARKS",
      "song": "Purple Phase",
      "label": "Transgressive",
      "timeslot": "05:30:00"
    },
    {
      "artist": "HAUSCHKA",
      "song": "Inventions",
      "label": "City Slang",
      "timeslot": "05:30:00"
    },
    {
      "artist": "LASTLINGS",
      "song": "Gravity",
      "label": "Liberation",
      "timeslot": "05:30:00"
    },
    {
      "artist": "LASTLINGS",
      "song": "Noise",
      "label": "Liberation",
      "timeslot": "05:30:00"
    },
    {
      "artist": "LASTLINGS",
      "song": "Perfect World",
      "label": "Liberation",
      "timeslot": "05:30:00"
    },
    {
      "artist": "PETER BIBBY",
      "song": "Bin Boy",
      "label": "Spinning Top",
      "timeslot": "06:00:00"
    },
    {
      "artist": "FANNING DEMPSEY NATIONAL PARK",
      "song": "Disconnect",
      "label": "Dew Process",
      "timeslot": "06:00:00"
    },
    {
      "artist": "SASAMI",
      "song": "Honeycrash",
      "label": "Domino",
      "timeslot": "06:00:00"
    },
    {
      "artist": "CHANEL LOREN",
      "song": "Ring Ring",
      "label": "Rubyworks / Columbia",
      "timeslot": "06:00:00"
    },
    {
      "artist": "BILLIE EILISH",
      "song": "Lunch",
      "label": "Interscope Records",
      "timeslot": "06:00:00"
    },
    {
      "artist": "ALLDAY ft. CUB SPORT",
      "song": "Miss You Still",
      "label": "Dew Process",
      "timeslot": "06:00:00"
    },
    {
      "artist": "PURPLE DISCO MACHINE and BENJAMIN INGROSSO",
      "song": "Honey Boy (ft. Nile Rodgers and Shenseea)",
      "label": "Sweat It Out",
      "timeslot": "06:00:00"
    },
    {
      "artist": "EMPIRE OF THE SUN",
      "song": "Music On The Radio",
      "label": "EMI",
      "timeslot": "06:00:00"
    },
    {
      "artist": "ELSY WAMEYO",
      "song": "UMVA",
      "label": "Independent",
      "timeslot": "06:00:00"
    },
    {
      "artist": "SKEGSS",
      "song": "Spaceman",
      "label": "Loma Vista",
      "timeslot": "06:30:00"
    },
    {
      "artist": "PARSNIP",
      "song": "The Babble",
      "label": null,
      "timeslot": "06:30:00"
    },
    {
      "artist": "THE BUOYS",
      "song": "Check Mate",
      "label": "Arcadia Records",
      "timeslot": "06:30:00"
    },
    {
      "artist": "DEEPFAITH",
      "song": "Sunshower666",
      "label": "Independent",
      "timeslot": "06:30:00"
    },
    {
      "artist": "GUM / AMBROSE KENNY-SMITH",
      "song": "Ill Times",
      "label": null,
      "timeslot": "06:30:00"
    },
    {
      "artist": "NICE BISCUIT",
      "song": "Rain",
      "label": "Bad Vibrations / Greenway Records",
      "timeslot": "06:30:00"
    },
    {
      "artist": "GINGER ROOT",
      "song": "No Problems",
      "label": "Ghostly International",
      "timeslot": "06:30:00"
    }
  ]
}