{
  "title": "Sunday night 26 January 2025 on ABC TV",
  "special": "The VAULT 1996 Hip Hop",
  "timeslot": "night",
  "date": "2025-01-26",
  "url": "https://www.abc.net.au/rage/playlist/sunday-night-26-january-2025-on-abc-tv/104856994",
  "tracks": [
    {
      "artist": "DJ KOOL",
      "song": "Let Me Clear My Throat",
      "label": "BMG",
      "timeslot": "00:30:00"
    },
    {
      "artist": "B. REAL, BUSTA RHYMES, COOLIO, LL COOL J",
      "song": "Hit 'Em High (The Monstars' Anthem)",
      "label": "Warner",
      "timeslot": "00:30:00"
    },
    {
      "artist": "SHAQUILLE O'NEAL",
      "song": "You Can't Stop The Reign",
      "label": "Universal",
      "timeslot": "00:30:00"
    },
    {
      "artist": "MC LYTE",
      "song": "Cold Rock A Party",
      "label": "Warner",
      "timeslot": "00:30:00"
    },
    {
      "artist": "LOST BOYZ",
      "song": "Jeeps, Lex Coups, Bimaz and Benz",
      "label": null,
      "timeslot": "00:30:00"
    },
    {
      "artist": "GHOSTFACE KILLAH",
      "song": "Motherless Child",
      "label": "Warner",
      "timeslot": "01:00:00"
    },
    {
      "artist": "BUSTA RHYMES",
      "song": "Woo-Hah!! (Got You All In Check)",
      "label": "Warner",
      "timeslot": "01:00:00"
    },
    {
      "artist": "DE LA SOUL",
      "song": "Stakes Is High",
      "label": "Fest/Mush",
      "timeslot": "01:00:00"
    },
    {
      "artist": "A TRIBE CALLED QUEST",
      "song": "Stressed Out",
      "label": "Mushroom",
      "timeslot": "01:00:00"
    },
    {
      "artist": "LL COOL J",
      "song": "Doin' It",
      "label": "Mercury",
      "timeslot": "01:00:00"
    },
    {
      "artist": "LL COOL J featuring TOTAL",
      "song": "Loungin'",
      "label": "Mercury",
      "timeslot": "01:00:00"
    },
    {
      "artist": "LL COOL J",
      "song": "Ain't Nobody",
      "label": "MCA)",
      "timeslot": "01:00:00"
    },
    {
      "artist": "DREAM WARRIORS",
      "song": "Float On",
      "label": "EMI",
      "timeslot": "01:30:00"
    },
    {
      "artist": "BONE, THUGS 'N' HARMONY",
      "song": "Tha Crossroads",
      "label": "Sony",
      "timeslot": "01:30:00"
    },
    {
      "artist": "OUTKAST",
      "song": "Elevators (Me and You)",
      "label": "BMG",
      "timeslot": "01:30:00"
    },
    {
      "artist": "SPEARHEAD",
      "song": "Why Oh Why",
      "label": "EMI",
      "timeslot": "01:30:00"
    },
    {
      "artist": "DLT FEATURING CHE FU",
      "song": "Chains",
      "label": "BMG",
      "timeslot": "01:30:00"
    },
    {
      "artist": "LUCIANO ft. THE JUNGLE BROTHERS",
      "song": "Who Could It Be",
      "label": "Island Jamaica",
      "timeslot": "01:30:00"
    },
    {
      "artist": "REFUGEE CAMP ALLSTARS",
      "song": "Rumble In The Jungle",
      "label": "Mercury",
      "timeslot": "01:30:00"
    },
    {
      "artist": "THE FUGEES",
      "song": "Ready Or Not",
      "label": "Sony",
      "timeslot": "02:00:00"
    },
    {
      "artist": "NAS featuring LAURYN HILL",
      "song": "If I Ruled The World",
      "label": "Sony",
      "timeslot": "02:00:00"
    },
    {
      "artist": "FOXY BROWN",
      "song": "I'll Be",
      "label": "Mercury",
      "timeslot": "02:00:00"
    },
    {
      "artist": "FOXY BROWN",
      "song": "Big Bad Mama",
      "label": "Mercury",
      "timeslot": "02:00:00"
    },
    {
      "artist": "FOXY BROWN featuring BLACKSTREET",
      "song": "Get Me Home",
      "label": "Mercury",
      "timeslot": "02:00:00"
    },
    {
      "artist": "DR DRE",
      "song": "Been There Done That",
      "label": "MCA)",
      "timeslot": "02:00:00"
    },
    {
      "artist": "XZIBIT",
      "song": "Paparazzi",
      "label": "BMG",
      "timeslot": "02:30:00"
    },
    {
      "artist": "ICE-T",
      "song": "I Must Stand",
      "label": "EMI",
      "timeslot": "02:30:00"
    },
    {
      "artist": "SNOOP DOGGY DOGG",
      "song": "Snoop's Upside Ya Head",
      "label": "MCA)",
      "timeslot": "02:30:00"
    },
    {
      "artist": "WARREN G",
      "song": "What's Love Got To Do With It",
      "label": "MCA)",
      "timeslot": "02:30:00"
    },
    {
      "artist": "MAKAVELI",
      "song": "To Live And Die In L.A.",
      "label": "MCA)",
      "timeslot": "02:30:00"
    },
    {
      "artist": "2 PAC",
      "song": "I Ain't Mad At Cha",
      "label": "Mercury",
      "timeslot": "02:30:00"
    },
    {
      "artist": "2 PAC featuring SNOOP DOGGY DOGG",
      "song": "2 Of Amerikaz Most Wanted",
      "label": "Universal",
      "timeslot": "02:30:00"
    },
    {
      "artist": "2 PAC ft. DR DRE",
      "song": "California Love",
      "label": "Mercury",
      "timeslot": "03:00:00"
    }
  ]
}