{
  "title": "Friday night 31 May 2024 on ABC TV",
  "url": "https://www.abc.net.au/rage/playlist/friday-night-31-may-2024-on-abc-tv/103921418",
  "special": "New Music Show",
  "timeslot": "night",
  "date": "2024-05-31",
  "tracks": [
    {
      "artist": "AMYL AND THE SNIFFERS",
      "song": "U Should Not Be Doing That",
      "label": "Virgin",
      "timeslot": "01:30:00"
    },
    {
      "artist": "GINGER ROOT",
      "song": "No Problems",
      "label": "Ghostly International",
      "timeslot": "01:30:00"
    },
    {
      "artist": "GUM / AMBROSE KENNY-SMITH",
      "song": "Ill Times",
      "label": null,
      "timeslot": "02:00:00"
    },
    {
      "artist": "PARTIBOI69",
      "song": "Double Drop",
      "label": "Independent",
      "timeslot": "02:00:00"
    },
    {
      "artist": "PURPLE DISCO MACHINE and BENJAMIN INGROSSO",
      "song": "Honey Boy (ft. Nile Rodgers and Shenseea)",
      "label": "Sweat It Out",
      "timeslot": "02:00:00"
    },
    {
      "artist": "CAMILA CABELLO ft. LIL NAS X",
      "song": "He Knows",
      "label": "Geffen / Interscope",
      "timeslot": "02:00:00"
    },
    {
      "artist": "GIMMY",
      "song": "Where Are You Going?",
      "label": "Third Eye Stimuli Records",
      "timeslot": "02:00:00"
    },
    {
      "artist": "OKAY KAYA",
      "song": "The Groke",
      "label": null,
      "timeslot": "02:00:00"
    },
    {
      "artist": "DAVE MASON",
      "song": "March Forward",
      "label": "Chapter",
      "timeslot": "02:00:00"
    },
    {
      "artist": "KAYPS and CALVIN BENNETT",
      "song": "Buon Giorno",
      "label": "Independent",
      "timeslot": "02:00:00"
    },
    {
      "artist": "BBNO$",
      "song": "It Boy",
      "label": "Independent",
      "timeslot": "02:00:00"
    },
    {
      "artist": "3%",
      "song": "Coming Home",
      "label": "1788 Records",
      "timeslot": "02:30:00"
    },
    {
      "artist": "PETER BIBBY",
      "song": "Bin Boy",
      "label": "Spinning Top",
      "timeslot": "02:30:00"
    },
    {
      "artist": "THE RUBENS",
      "song": "Black Balloon",
      "label": "Ivy League",
      "timeslot": "02:30:00"
    },
    {
      "artist": "BATTLESNAKE",
      "song": "The Key Of Solomon",
      "label": "Independent",
      "timeslot": "02:30:00"
    },
    {
      "artist": "RM",
      "song": "LOST!",
      "label": "BigHit",
      "timeslot": "02:30:00"
    },
    {
      "artist": "REMI WOLF",
      "song": "Toro",
      "label": "Island Records",
      "timeslot": "02:30:00"
    },
    {
      "artist": "NICE BISCUIT",
      "song": "Rain",
      "label": "Bad Vibrations / Greenway Records",
      "timeslot": "02:30:00"
    },
    {
      "artist": "EARTH TONGUE",
      "song": "Out Of This Hell",
      "label": "Stolen Body Records",
      "timeslot": "03:00:00"
    },
    {
      "artist": "OCEAN GROVE",
      "song": "Fly Away",
      "label": "ODDWORLD Records / Sharptone Records",
      "timeslot": "03:00:00"
    },
    {
      "artist": "STAND ATLANTIC",
      "song": "Love U Anyway",
      "label": "Hopeless Records",
      "timeslot": "03:00:00"
    },
    {
      "artist": "SAME PAINS",
      "song": "Kin Of Death",
      "label": "Independent",
      "timeslot": "03:00:00"
    },
    {
      "artist": "SANTPOORT ft. LITTLE GREEN and KENNEBEC",
      "song": "Come To Life",
      "label": "Independent",
      "timeslot": "03:00:00"
    },
    {
      "artist": "PARSNIP",
      "song": "The Babble",
      "label": null,
      "timeslot": "03:00:00"
    },
    {
      "artist": "POST MALONE ft. MORGAN WALLEN",
      "song": "I Had Some Help",
      "label": "Mercury Records",
      "timeslot": "03:00:00"
    },
    {
      "artist": "DEEPFAITH",
      "song": "Sunshower666",
      "label": "Independent",
      "timeslot": "03:00:00"
    },
    {
      "artist": "CHARLI XCX",
      "song": "360",
      "label": "Atlantic",
      "timeslot": "03:00:00"
    },
    {
      "artist": "CHILDISH GAMBINO ft. YOUNG NUDY",
      "song": "Little Foot Big Foot",
      "label": "Liberator",
      "timeslot": "03:30:00"
    },
    {
      "artist": "DUNE RATS",
      "song": "Cheapskate",
      "label": "BMG",
      "timeslot": "03:30:00"
    },
    {
      "artist": "EMPIRE OF THE SUN",
      "song": "Music On The Radio",
      "label": "EMI",
      "timeslot": "03:30:00"
    },
    {
      "artist": "ROWENA WISE",
      "song": "Indifferent",
      "label": "Beloved Recordings",
      "timeslot": "03:30:00"
    },
    {
      "artist": "SASAMI",
      "song": "Honeycrash",
      "label": "Domino",
      "timeslot": "03:30:00"
    },
    {
      "artist": "WASHED OUT",
      "song": "The Hardest Part",
      "label": "Sub Pop",
      "timeslot": "03:30:00"
    },
    {
      "artist": "CHANEL LOREN",
      "song": "Ring Ring",
      "label": "Rubyworks / Columbia",
      "timeslot": "03:30:00"
    },
    {
      "artist": "BILLIE EILISH",
      "song": "Lunch",
      "label": "Interscope Records",
      "timeslot": "03:30:00"
    },
    {
      "artist": "YOUNGER THAN ME",
      "song": "With Every Heartbeat",
      "label": "Independent",
      "timeslot": "04:00:00"
    },
    {
      "artist": "HOZIER",
      "song": "Too Sweet",
      "label": "Rubyworks / Columbia",
      "timeslot": "04:00:00"
    },
    {
      "artist": "ANGUS and JULIA STONE",
      "song": "Down To The Sea",
      "label": "Sony",
      "timeslot": "04:00:00"
    },
    {
      "artist": "Y.O.G.A. and AVIVA",
      "song": "Rodeo",
      "label": "Hoedown Records",
      "timeslot": "04:00:00"
    },
    {
      "artist": "IPOD",
      "song": "Friend Crush",
      "label": "Independent",
      "timeslot": "04:00:00"
    },
    {
      "artist": "ANDREW GURRUWIWI BAND",
      "song": "Yaa Djamarrkuli",
      "label": "Independent",
      "timeslot": "04:00:00"
    },
    {
      "artist": "CONG JOSIE",
      "song": "1300 Scorpio",
      "label": "It Records",
      "timeslot": "04:00:00"
    },
    {
      "artist": "FUKHED",
      "song": "No C No A",
      "label": "Independent",
      "timeslot": "04:00:00"
    },
    {
      "artist": "CHEAP-SKATE",
      "song": "Cellphone",
      "label": "Independent",
      "timeslot": "04:30:00"
    },
    {
      "artist": "SOFI TUKKER",
      "song": "Throw Some Ass",
      "label": "Virgin",
      "timeslot": "04:30:00"
    },
    {
      "artist": "FANNING DEMPSEY NATIONAL PARK",
      "song": "Disconnect",
      "label": "Dew Process",
      "timeslot": "04:30:00"
    },
    {
      "artist": "MAGNETS",
      "song": "Speak",
      "label": "Independent",
      "timeslot": "04:30:00"
    },
    {
      "artist": "HENNESSEY ROSE",
      "song": "A Hundred Years",
      "label": "Dinosaur City",
      "timeslot": "04:30:00"
    },
    {
      "artist": "MABEL and SHYGIRL",
      "song": "Look At My Body (Pt. II)",
      "label": "Universal",
      "timeslot": "04:30:00"
    },
    {
      "artist": "FONTAINES D.C.",
      "song": "Starburster",
      "label": "XL",
      "timeslot": "04:30:00"
    },
    {
      "artist": "BODYSYNC",
      "song": "Rock It",
      "label": "Buddies Inc.",
      "timeslot": "04:30:00"
    },
    {
      "artist": "SKEGSS",
      "song": "Spaceman",
      "label": "Loma Vista",
      "timeslot": "05:00:00"
    },
    {
      "artist": "NICK WARD",
      "song": "Shooting Star (censored version)",
      "label": "EMI",
      "timeslot": "05:00:00"
    },
    {
      "artist": "SANTPOORT ft. JONTI",
      "song": "In My Dreams",
      "label": "Independent",
      "timeslot": "05:00:00"
    },
    {
      "artist": "GIMMY",
      "song": "Bathrooms",
      "label": "Third Eye Stimuli Records",
      "timeslot": "05:00:00"
    },
    {
      "artist": "ELSY WAMEYO",
      "song": "UMVA",
      "label": "Independent",
      "timeslot": "05:00:00"
    },
    {
      "artist": "SIS",
      "song": "Bow To Your Wilderness",
      "label": "Native Cat Recordings",
      "timeslot": "05:00:00"
    },
    {
      "artist": "ROYEL OTIS",
      "song": "Foam",
      "label": "Ourness",
      "timeslot": "05:00:00"
    },
    {
      "artist": "PHOEBE GO",
      "song": "Stupid",
      "label": "AWAL",
      "timeslot": "05:00:00"
    },
    {
      "artist": "BEN LEE",
      "song": "Heavy Metal",
      "label": "Weirder Together",
      "timeslot": "05:00:00"
    },
    {
      "artist": "ODETTE",
      "song": "Reverence",
      "label": "Independent",
      "timeslot": "05:30:00"
    },
    {
      "artist": "POND",
      "song": "(I'm) Stung",
      "label": "Spinning Top",
      "timeslot": "05:30:00"
    },
    {
      "artist": "BEABADOOBEE",
      "song": "Take A Bite",
      "label": "Dirty Hit",
      "timeslot": "05:30:00"
    },
    {
      "artist": "JADA WEAZEL",
      "song": "Send My Love",
      "label": "EMI",
      "timeslot": "05:30:00"
    },
    {
      "artist": "ALLDAY ft. CUB SPORT",
      "song": "Miss You Still",
      "label": "Dew Process",
      "timeslot": "05:30:00"
    },
    {
      "artist": "THE BUOYS",
      "song": "Check Mate",
      "label": "Arcadia Records",
      "timeslot": "05:30:00"
    },
    {
      "artist": "KAT EDWARDS",
      "song": "Waiting Room",
      "label": "BMG",
      "timeslot": "05:30:00"
    },
    {
      "artist": "MY CHERIE",
      "song": "Darkness and Gold",
      "label": "Independent",
      "timeslot": "05:30:00"
    },
    {
      "artist": "HOCKEY DAD",
      "song": "Safety Pin",
      "label": "Farmer And The Owl",
      "timeslot": "05:30:00"
    }
  ]
}